bpsai_pair/__init__.py
bpsai_pair/__main__.py
bpsai_pair/cli.py
bpsai_pair/compaction.py
bpsai_pair/init_bundled_cli.py
bpsai_pair/migrate.py
bpsai_pair/session.py
bpsai_pair/tokens.py
bpsai_pair/benchmarks/__init__.py
bpsai_pair/benchmarks/reports.py
bpsai_pair/benchmarks/runner.py
bpsai_pair/benchmarks/validation.py
bpsai_pair/commands/__init__.py
bpsai_pair/commands/arch.py
bpsai_pair/commands/audit.py
bpsai_pair/commands/benchmark.py
bpsai_pair/commands/budget.py
bpsai_pair/commands/cache.py
bpsai_pair/commands/compaction_commands.py
bpsai_pair/commands/config.py
bpsai_pair/commands/config_cmd.py
bpsai_pair/commands/containment_commands.py
bpsai_pair/commands/context_commands.py
bpsai_pair/commands/core.py
bpsai_pair/commands/enforce.py
bpsai_pair/commands/init_commands.py
bpsai_pair/commands/license.py
bpsai_pair/commands/mcp.py
bpsai_pair/commands/metrics.py
bpsai_pair/commands/orchestrate.py
bpsai_pair/commands/preset.py
bpsai_pair/commands/security.py
bpsai_pair/commands/session.py
bpsai_pair/commands/session_check.py
bpsai_pair/commands/state.py
bpsai_pair/commands/timer.py
bpsai_pair/commands/upgrade.py
bpsai_pair/commands/validation_commands.py
bpsai_pair/commands/wizard.py
bpsai_pair/context/__init__.py
bpsai_pair/context/cache.py
bpsai_pair/context/loader.py
bpsai_pair/core/__init__.py
bpsai_pair/core/bypass_log.py
bpsai_pair/core/config.py
bpsai_pair/core/config_defaults.py
bpsai_pair/core/config_helpers.py
bpsai_pair/core/config_loader.py
bpsai_pair/core/config_templates.py
bpsai_pair/core/config_validator.py
bpsai_pair/core/constants.py
bpsai_pair/core/deprecation.py
bpsai_pair/core/enforcement.py
bpsai_pair/core/enforcement_analyzer.py
bpsai_pair/core/enforcement_checker.py
bpsai_pair/core/enforcement_models.py
bpsai_pair/core/enforcement_utils.py
bpsai_pair/core/hooks.py
bpsai_pair/core/ops.py
bpsai_pair/core/preconditions.py
bpsai_pair/core/preferences.py
bpsai_pair/core/presets.py
bpsai_pair/core/routing.py
bpsai_pair/core/task_state.py
bpsai_pair-2.10.6.dist-info/licenses/LICENSE
bpsai_pair-2.10.6.dist-info/METADATA
bpsai_pair-2.10.6.dist-info/WHEEL
bpsai_pair-2.10.6.dist-info/entry_points.txt
bpsai_pair-2.10.6.dist-info/top_level.txt
bpsai_pair-2.10.6.dist-info/RECORD
