Metadata-Version: 2.4
Name: bpsai-pair
Version: 2.10.6
Summary: AI-augmented pair programming framework with 182+ CLI commands for planning, orchestration, Trello/GitHub integration, and autonomous workflows
Author-email: BPS AI Software <dev@bpsai.com>
License-Expression: LicenseRef-Proprietary
Project-URL: Homepage, https://github.com/BPSAI/paircoder
Project-URL: Documentation, https://github.com/BPSAI/paircoder#readme
Project-URL: Repository, https://github.com/BPSAI/paircoder
Project-URL: Issues, https://github.com/BPSAI/paircoder/issues
Project-URL: Changelog, https://github.com/BPSAI/paircoder/blob/main/CHANGELOG.md
Keywords: ai,pair-programming,cli,claude,gpt,codex,gemini,mcp,trello,github,autonomous,workflow,planning,tasks
Classifier: Development Status :: 4 - Beta
Classifier: Environment :: Console
Classifier: Intended Audience :: Developers
Classifier: Operating System :: OS Independent
Classifier: Programming Language :: Python :: 3
Classifier: Programming Language :: Python :: 3.11
Classifier: Programming Language :: Python :: 3.12
Classifier: Programming Language :: Python :: 3.13
Classifier: Topic :: Software Development
Classifier: Topic :: Software Development :: Build Tools
Classifier: Topic :: Software Development :: Version Control :: Git
Classifier: Typing :: Typed
Requires-Python: >=3.10
License-File: LICENSE
Requires-Dist: typer>=0.12
Requires-Dist: rich>=13.7
Requires-Dist: pyyaml>=6.0
Requires-Dist: tiktoken>=0.5.0
Requires-Dist: pydantic>=2.0
Requires-Dist: cryptography>=41.0
Requires-Dist: fastapi>=0.109.0
Requires-Dist: jinja2>=3.1.0
Requires-Dist: uvicorn>=0.27.0
Requires-Dist: sse-starlette>=1.6.0
Requires-Dist: toggl>=0.1.0
Requires-Dist: anthropic>=0.76.0
Provides-Extra: trello
Requires-Dist: py-trello>=0.19.0; extra == "trello"
Provides-Extra: github
Requires-Dist: PyGithub>=2.1; extra == "github"
Provides-Extra: timer
Requires-Dist: toggl>=0.1.0; extra == "timer"
Provides-Extra: mcp
Requires-Dist: mcp>=1.0.0; extra == "mcp"
Provides-Extra: docs
Requires-Dist: sphinx>=7.0; extra == "docs"
Requires-Dist: sphinx-rtd-theme>=2.0; extra == "docs"
Requires-Dist: sphinx-autodoc-typehints>=2.0; extra == "docs"
Requires-Dist: sphinx-copybutton>=0.5; extra == "docs"
Requires-Dist: myst-parser>=2.0; extra == "docs"
Requires-Dist: sphinx-click>=5.0; extra == "docs"
Provides-Extra: sandbox
Requires-Dist: docker>=7.0.0; extra == "sandbox"
Requires-Dist: dockerpty>=0.4.1; extra == "sandbox"
Provides-Extra: wizard
Requires-Dist: anthropic>=0.76.0; extra == "wizard"
Provides-Extra: all
Requires-Dist: py-trello>=0.19.0; extra == "all"
Requires-Dist: mcp>=1.0.0; extra == "all"
Requires-Dist: docker>=7.0.0; extra == "all"
Requires-Dist: dockerpty>=0.4.1; extra == "all"
Provides-Extra: integrations
Requires-Dist: py-trello>=0.19.0; extra == "integrations"
Dynamic: license-file
